corsheaders/__init__.py
corsheaders/defaults.py
corsheaders/middleware.py
corsheaders/models.py
corsheaders/tests.py
django_cors_headers_multi-1.2.0.dist-info/DESCRIPTION.rst
django_cors_headers_multi-1.2.0.dist-info/METADATA
django_cors_headers_multi-1.2.0.dist-info/RECORD
django_cors_headers_multi-1.2.0.dist-info/WHEEL
django_cors_headers_multi-1.2.0.dist-info/metadata.json
django_cors_headers_multi-1.2.0.dist-info/top_level.txt
