Metadata-Version: 2.0
Name: django-cors-headers-multi
Version: 1.2.0
Summary: django-cors-headers is a Django application for handling the server headers required for Cross-Origin Resource Sharing (CORS).
Home-page: https://github.com/mstriemer/django-cors-headers
Author: Otto Yiu
Author-email: otto@live.ca
License: MIT License
Keywords: django cors middleware rest api
Platform: any
Classifier: Development Status :: 5 - Production/Stable
Classifier: Environment :: Web Environment
Classifier: Framework :: Django
Classifier: Intended Audience :: Developers
Classifier: License :: OSI Approved :: MIT License
Classifier: Operating System :: OS Independent
Classifier: Programming Language :: Python
Classifier: Programming Language :: Python :: 2
Classifier: Programming Language :: Python :: 2.6
Classifier: Programming Language :: Python :: 2.7
Classifier: Programming Language :: Python :: 3
Classifier: Programming Language :: Python :: 3.2
Classifier: Programming Language :: Python :: 3.3
Classifier: Programming Language :: Python :: 3.4
Classifier: Topic :: Software Development :: Libraries :: Application Frameworks
Classifier: Topic :: Software Development :: Libraries :: Python Modules
